yavin
