Metadata-Version: 2.1
Name: yavin
Version: 1.0.1
Summary: Python API client for the Yavin API
Home-page: https://github.com/yavinapi/yavin-python-client
Author: Yavin
Author-email: tech@yavin.com
License: MIT
Platform: UNKNOWN
Classifier: License :: OSI Approved :: MIT License
Classifier: Programming Language :: Python :: 3
Classifier: Programming Language :: Python :: 3.5
Classifier: Programming Language :: Python :: 3.6
Classifier: Programming Language :: Python :: 3.7
Classifier: Programming Language :: Python :: 3.8
